geo_adjacency/__init__.py
geo_adjacency/adjacency.py
geo_adjacency/exception.py
geo_adjacency/utils.py
geo_adjacency-1.2.2.dist-info/LICENSE
geo_adjacency-1.2.2.dist-info/METADATA
geo_adjacency-1.2.2.dist-info/WHEEL
geo_adjacency-1.2.2.dist-info/RECORD
