Metadata-Version: 2.3
Name: geo-adjacency
Version: 1.2.2
Summary: A package to determine which geometries are adjacent to each other, accounting for obstacles and gaps between features.
License: MIT
Keywords: voronoi,adjacency,geospatial,geometry
Author: Andrew Smyth
Author-email: andrew.j.smyth.89@gmail.com
Requires-Python: >=3.9,<3.13
Classifier: Development Status :: 4 - Beta
Classifier: Intended Audience :: Science/Research
Classifier: License :: OSI Approved :: MIT License
Classifier: Operating System :: OS Independent
Classifier: Programming Language :: Python
Classifier: Programming Language :: Python :: 3
Classifier: Programming Language :: Python :: 3.9
Classifier: Programming Language :: Python :: 3.10
Classifier: Programming Language :: Python :: 3.11
Classifier: Programming Language :: Python :: 3.12
Classifier: Topic :: Scientific/Engineering
Classifier: Topic :: Scientific/Engineering :: GIS
Requires-Dist: matplotlib (>=3.8.1)
Requires-Dist: numpy (>=1.26.2)
Requires-Dist: scipy (>=1.11.3)
Requires-Dist: setuptools (>=69.0.0)
Requires-Dist: shapely (>=2.0.2)
Project-URL: Documentation, https://asmyth01.github.io/geo-adjacency/
Project-URL: Homepage, https://asmyth01.github.io/geo-adjacency/
Project-URL: Repository, https://github.com/andrewsmyth/geo-adjacency
